dungeonmasterai/__init__.py
dungeonmasterai-0.1.dist-info/LICENSE
dungeonmasterai-0.1.dist-info/METADATA
dungeonmasterai-0.1.dist-info/WHEEL
dungeonmasterai-0.1.dist-info/top_level.txt
dungeonmasterai-0.1.dist-info/RECORD
