Metadata-Version: 2.1
Name: dungeonmasterai
Version: 0.1
Summary: A python module
Author: Matthew Sanchez
Author-email: 
Classifier: Programming Language :: Python :: 3
Classifier: License :: OSI Approved :: MIT License
Classifier: Operating System :: OS Independent
Requires-Python: >=3.10
License-File: LICENSE
